wgus/__init__.py
wgus/constants.py
wgus/metadata.py
wgus/patches_chains.py
wgus/requests.py
wgus-0.0.12.dist-info/WHEEL
wgus-0.0.12.dist-info/METADATA
wgus-0.0.12.dist-info/RECORD
