Metadata-Version: 2.4
Name: wgus
Version: 0.0.12
Summary: API for Wargaming Update Service (WGUS)
Home-page: https://github.com/IzeBerg/wgus
Author: Renat Iliev
Author-email: me@izeberg.me
Requires-Python: >=3.8
Requires-Dist: pydantic >=1.8.2
Requires-Dist: pytest >=7.0.0
Requires-Dist: pytest-asyncio >=0.16.0
Requires-Dist: aiohttp >=3.7.4.post0
Requires-Dist: aiodns >=3.0.0
Requires-Dist: pytest >=7.0.0 ; extra == "test"
Requires-Dist: mypy ==0.960 ; extra == "test"
Requires-Dist: flake8 >=3.8.3,<4.0.0 ; extra == "test"
Requires-Dist: black >=22.8.0 ; extra == "test"
Requires-Dist: isort >=5.0.6,<6.0.0 ; extra == "test"
Provides-Extra: test
